odoo/addons/hr_contract_update_overtime/README.rst
odoo/addons/hr_contract_update_overtime/__init__.py
odoo/addons/hr_contract_update_overtime/__manifest__.py
odoo/addons/hr_contract_update_overtime/data/hr_contract_history_data.xml
odoo/addons/hr_contract_update_overtime/i18n/es.po
odoo/addons/hr_contract_update_overtime/i18n/hr_contract_update_overtime.pot
odoo/addons/hr_contract_update_overtime/i18n/it.po
odoo/addons/hr_contract_update_overtime/models/__init__.py
odoo/addons/hr_contract_update_overtime/models/hr_contract.py
odoo/addons/hr_contract_update_overtime/readme/CONTEXT.md
odoo/addons/hr_contract_update_overtime/readme/CONTRIBUTORS.md
odoo/addons/hr_contract_update_overtime/readme/DESCRIPTION.md
odoo/addons/hr_contract_update_overtime/readme/USAGE.md
odoo/addons/hr_contract_update_overtime/static/description/icon.png
odoo/addons/hr_contract_update_overtime/static/description/index.html
odoo/addons/hr_contract_update_overtime/tests/__init__.py
odoo/addons/hr_contract_update_overtime/tests/test_hr_contract_update_overtime.py
odoo_addon_hr_contract_update_overtime-18.0.1.0.1.dist-info/METADATA
odoo_addon_hr_contract_update_overtime-18.0.1.0.1.dist-info/WHEEL
odoo_addon_hr_contract_update_overtime-18.0.1.0.1.dist-info/top_level.txt
odoo_addon_hr_contract_update_overtime-18.0.1.0.1.dist-info/RECORD
